{
  "name": "Откос",
  "slug": "windowReveal",
  "data": [
    {
      "id": 200,
      "name": "200 мм",
      "price": {
        "1": 2180,
        "2": 2120,
        "3": 2120,
        "4": 2700,
        "5": 2810
      }
    },
    {
      "id": 250,
      "name": "250 мм",
      "price": {
        "1": 2180,
        "2": 2120,
        "3": 2120,
        "4": 2700,
        "5": 2810
      }
    },
    {
      "id": 300,
      "name": "300 мм",
      "price": {
        "1": 2180,
        "2": 2120,
        "3": 2120,
        "4": 2700,
        "5": 2810
      }
    },
    {
      "id": 400,
      "name": "400 мм",
      "price": {
        "1": 3080,
        "2": 3020,
        "3": 3020,
        "4": 4500,
        "5": 4610
      }
    },
    {
      "id": 500,
      "name": "500 мм",
      "price": {
        "1": 3080,
        "2": 3020,
        "3": 3020,
        "4": 4500,
        "5": 4610
      }
    },
    {
      "id": 600,
      "name": "600 мм",
      "price": {
        "1": 3080,
        "2": 3020,
        "3": 3020,
        "4": 4500,
        "5": 4610
      }
    }
  ]
}
